pyqt_file_list_widget/__init__.py
pyqt_file_list_widget/fileListWidget.py
pyqt_file_list_widget-0.0.1.dist-info/LICENSE
pyqt_file_list_widget-0.0.1.dist-info/METADATA
pyqt_file_list_widget-0.0.1.dist-info/WHEEL
pyqt_file_list_widget-0.0.1.dist-info/top_level.txt
pyqt_file_list_widget-0.0.1.dist-info/RECORD
