Metadata-Version: 2.1
Name: pyqt-file-list-widget
Version: 0.0.1
Summary: PyQt QListWidget for files (being able to drop the files based on user-defined extensions)
Home-page: https://github.com/yjg30737/pyqt-file-list-widget.git
Author: Jung Gyu Yoon
Author-email: yjg30737@gmail.com
License: MIT
Platform: UNKNOWN
License-File: LICENSE
Requires-Dist: PyQt5 (>=5.8)
Requires-Dist: pyqt-tooltip-list-widget (>=0.0.1)
Requires-Dist: pyqt-files-already-exists-dialog (>=0.0.1)
